{
  "arrangements-circular.data.js": 60,
  "arrangements-floor.data.js": 45,
  "arrangements-linear.data.js": 60,
  "coding-letter-shift.data.js": 60,
  "coding-symbol.data.js": 45,
  "logic-plaza-flashcards.data.js": 0,
  "logic-plaza-study-notes.data.js": 0,
  "logic-statement.data.js": 60,
  "logic-syllogism.data.js": 69,
  "logic-venn.data.js": 45,
  "relations-blood.data.js": 60,
  "relations-direction.data.js": 60,
  "series-alphabet.data.js": 60,
  "series-alphanumeric.data.js": 45,
  "series-number.data.js": 75,
  "visual-mirror-water.data.js": 60,
  "visual-paper-pattern.data.js": 45
}